pywincmdtheme
