Metadata-Version: 1.0
Name: pywincmdtheme
Version: 0.1.5
Summary: Tool that can change color theme for windows cmd and powershell. Uses ~/.Xresources file that defines 16 standard colors, background color and foreground color.
Home-page: http://bitbucket.org/eyeofhell/pywincmdtheme
Author: Grigory Petrov
Author-email: grigory.v.p@gmail.com
License: GPLv3
Platform: UNKNOWN
Classifier: Development Status :: 2 - Pre-Alpha
Classifier: Environment :: Console
Classifier: Intended Audience :: End Users/Desktop
Classifier: License :: OSI Approved :: GNU General Public License v3 (GPLv3)
Classifier: Natural Language :: English
Classifier: Operating System :: Microsoft :: Windows
Classifier: Programming Language :: Python :: 2.7
Classifier: Topic :: Desktop Environment
